NeelKrypt/__init__.py
NeelKrypt-777.dist-info/METADATA
NeelKrypt-777.dist-info/WHEEL
NeelKrypt-777.dist-info/top_level.txt
NeelKrypt-777.dist-info/RECORD
